{
  "package-0/uncore|uJ": 30640,
  "instructions": 733236,
  "package-0/dram|uJ": 75444570,
  "uncore|uJ": 30640,
  "cycles": 4315354,
  "dram|mW": 1646,
  "cache-misses": 124999,
  "package|uJ": 718457268,
  "branch-misses": 0,
  "package-0/core|mW": 13473,
  "device|uJ": 793901838,
  "core|uJ": 617387763,
  "psys|mW": 42589,
  "psys|uJ": 1951538950,
  "package-0|uJ": 718457268,
  "duration|ns": 45821686836,
  "branches": 535467,
  "core|mW": 13473,
  "device|mW": 17325,
  "package-0/dram|mW": 1646,
  "dram|uJ": 75444570,
  "package-0/core|uJ": 617387763,
  "cache-reference": 344354,
  "package-0/uncore|mW": 0,
  "package-0|mW": 15679,
  "package|mW": 15679,
  "uncore|mW": 0
}