{
    "com.google.gson.functional.MapTest-testWriteMapsWithEmptyStringKey": {
        "energy": 40222,
        "duration": 693170.8888888889,
        "dram": 3149.222222222222,
        "iteration": 18,
        "stdev": 3879.9835118810925
    },
    "com.google.gson.functional.ObjectTest-testNestedSerialization": {
        "energy": 37231,
        "duration": 1005064.42,
        "dram": 3149.32,
        "iteration": 50,
        "stdev": 4517.002975248079
    },
    "com.google.gson.JsonParserTest-testReadWriteTwoObjects": {
        "energy": 42969,
        "duration": 4086128.4805194805,
        "dram": 12865.675324675325,
        "iteration": 77,
        "stdev": 373249.4801568247
    },
    "com.google.gson.stream.JsonWriterTest-testPrettyPrintArray": {
        "energy": 39978,
        "duration": 572858.68,
        "dram": 2302.28,
        "iteration": 25,
        "stdev": 3680.126563041005
    },
    "com.google.gson.functional.TypeVariableTest-testBasicTypeVariables": {
        "energy": 40588,
        "duration": 1163837.9682539683,
        "dram": 3606.1746031746034,
        "iteration": 63,
        "stdev": 29823.246159912564
    },
    "com.google.gson.OverrideCoreTypeAdaptersTest-testOverridePrimitiveBooleanAdapter": {
        "energy": 37964,
        "duration": 1035087.875,
        "dram": 2338.5,
        "iteration": 24,
        "stdev": 30225.378423327198
    },
    "com.google.gson.functional.TypeVariableTest-testAdvancedTypeVariables": {
        "energy": 65795,
        "duration": 4123885.6565656564,
        "dram": 12713.40404040404,
        "iteration": 99,
        "stdev": 329071.7808447842
    },
    "com.google.gson.functional.ObjectTest-testArrayOfObjectsAsFields": {
        "energy": 37781,
        "duration": 1088637.621212121,
        "dram": 3295.7727272727275,
        "iteration": 66,
        "stdev": 7872.769146566153
    },
    "com.google.gson.functional.UncategorizedTest-testGsonInstanceReusableForSerializationAndDeserialization": {
        "energy": 39673,
        "duration": 844724.5789473684,
        "dram": 3064.9210526315787,
        "iteration": 38,
        "stdev": 4160.300164298691
    },
    "com.google.gson.functional.EscapingTest-testGsonDoubleDeserialization": {
        "energy": 38330,
        "duration": 1185023.875,
        "dram": 3192.55,
        "iteration": 40,
        "stdev": 4437.166961023667
    },
    "com.google.gson.functional.UncategorizedTest-testStaticFieldsAreNotSerialized": {
        "energy": 40589,
        "duration": 1269859.4523809524,
        "dram": 3761.9761904761904,
        "iteration": 42,
        "stdev": 74367.45424780465
    },
    "com.google.gson.functional.MapAsArrayTypeAdapterTest-testSerializeComplexMapWithTypeAdapter": {
        "energy": 89294,
        "duration": 4541354.01010101,
        "dram": 14236.272727272728,
        "iteration": 99,
        "stdev": 310336.0921832921
    },
    "com.google.gson.functional.EscapingTest-testEscapingObjectFields": {
        "energy": 41259,
        "duration": 975539.8627450981,
        "dram": 3251.176470588235,
        "iteration": 51,
        "stdev": 11365.319246360974
    },
    "com.google.gson.functional.JsonTreeTest-testJsonTreeToString": {
        "energy": 41687,
        "duration": 1907373.4743589743,
        "dram": 5776.5641025641025,
        "iteration": 78,
        "stdev": 43089.14467863217
    },
    "com.google.gson.functional.TypeVariableTest-testTypeVariablesViaTypeParameter": {
        "energy": 42053,
        "duration": 1482269.1648351648,
        "dram": 4374.472527472528,
        "iteration": 91,
        "stdev": 13715.298443605749
    },
    "com.google.gson.functional.PrettyPrintingTest-testPrettyPrintArrayOfObjects": {
        "energy": 39978,
        "duration": 1139038.4193548388,
        "dram": 3515.532258064516,
        "iteration": 62,
        "stdev": 9629.76706144278
    },
    "com.google.gson.functional.DefaultTypeAdaptersTest-testNullSerialization": {
        "energy": 1035337,
        "duration": 20122456.494949494,
        "dram": 64848.9595959596,
        "iteration": 99,
        "stdev": 548817.8264088004
    },
    "com.google.gson.functional.CollectionTest-testWildcardCollectionField": {
        "energy": 43457,
        "duration": 2761843.8313253014,
        "dram": 8410.734939759037,
        "iteration": 83,
        "stdev": 83378.57398265829
    },
    "com.google.gson.functional.JsonTreeTest-testToJsonTreeObjectType": {
        "energy": 40283,
        "duration": 1262024.4561403508,
        "dram": 3356.9298245614036,
        "iteration": 57,
        "stdev": 27247.059874968185
    },
    "com.google.gson.functional.ObjectTest-testArrayOfArraysSerialization": {
        "energy": 39185,
        "duration": 1173767.3780487804,
        "dram": 3352.182926829268,
        "iteration": 82,
        "stdev": 5734.646273724407
    },
    "com.google.gson.functional.ParameterizedTypesTest-testTypesWithMultipleParametersSerialization": {
        "energy": 79346,
        "duration": 2593136.626262626,
        "dram": 7485.343434343435,
        "iteration": 99,
        "stdev": 31135.159207140634
    },
    "com.google.gson.internal.bind.JsonTreeWriterTest-testStrictNansAndInfinities": {
        "energy": 40710,
        "duration": 705909.6,
        "dram": 2656.9,
        "iteration": 20,
        "stdev": 14988.003614891477
    },
    "com.google.gson.functional.PrettyPrintingTest-testPrettyPrintList": {
        "energy": 44495,
        "duration": 2723736.1413043477,
        "dram": 8038.0,
        "iteration": 92,
        "stdev": 113794.62411173464
    },
    "com.google.gson.stream.JsonWriterTest-testDoubles": {
        "energy": 40283,
        "duration": 980917.7608695652,
        "dram": 3077.2391304347825,
        "iteration": 46,
        "stdev": 7984.40100773179
    },
    "com.google.gson.functional.InheritanceTest-testSubClassSerialization": {
        "energy": 40711,
        "duration": 1357580.6966292134,
        "dram": 3533.9662921348313,
        "iteration": 89,
        "stdev": 10616.912662505629
    },
    "com.google.gson.functional.JsonTreeTest-testToJsonTree": {
        "energy": 43640,
        "duration": 2737744.2786885244,
        "dram": 8313.704918032787,
        "iteration": 61,
        "stdev": 133892.0405188847
    },
    "com.google.gson.functional.DelegateTypeAdapterTest-testDelegateInvoked": {
        "energy": 69641,
        "duration": 2938999.714285714,
        "dram": 8723.632653061224,
        "iteration": 98,
        "stdev": 120677.38133653438
    },
    "com.google.gson.functional.ReadersWritersTest-testReadWriteTwoObjects": {
        "energy": 41260,
        "duration": 1356886.9714285715,
        "dram": 4161.585714285714,
        "iteration": 70,
        "stdev": 25694.384448464814
    },
    "com.google.gson.functional.CollectionTest-testRawCollectionSerialization": {
        "energy": 38147,
        "duration": 832382.7894736842,
        "dram": 2672.684210526316,
        "iteration": 38,
        "stdev": 4097.038710663581
    },
    "com.google.gson.internal.bind.JsonTreeWriterTest-testLenientNansAndInfinities": {
        "energy": 42847,
        "duration": 1357314.896551724,
        "dram": 4285.689655172414,
        "iteration": 29,
        "stdev": 73658.29568557239
    },
    "com.google.gson.functional.ArrayTest-testObjectArrayWithNonPrimitivesSerialization": {
        "energy": 40344,
        "duration": 1257136.475409836,
        "dram": 3592.4590163934427,
        "iteration": 61,
        "stdev": 10819.819237574222
    },
    "com.google.gson.functional.CollectionTest-testCollectionOfBagOfPrimitivesSerialization": {
        "energy": 40527,
        "duration": 1458634.085106383,
        "dram": 3166.5106382978724,
        "iteration": 47,
        "stdev": 8512.837400615936
    },
    "com.google.gson.functional.SecurityTest-testNonExecutableJsonSerialization": {
        "energy": 41077,
        "duration": 4673911.457142857,
        "dram": 15313.028571428571,
        "iteration": 35,
        "stdev": 411376.4992343969
    },
    "com.google.gson.functional.PrintFormattingTest-testCompactFormattingLeavesNoWhiteSpace": {
        "energy": 43274,
        "duration": 2269176.925,
        "dram": 6696.6125,
        "iteration": 80,
        "stdev": 95920.3927318606
    },
    "com.google.gson.stream.JsonWriterTest-testPrettyPrintObject": {
        "energy": 38880,
        "duration": 554188.8260869565,
        "dram": 2120.782608695652,
        "iteration": 23,
        "stdev": 4020.2158530016645
    },
    "com.google.gson.functional.ObjectTest-testBagOfPrimitivesSerialization": {
        "energy": 39001,
        "duration": 1694734.2564102565,
        "dram": 4567.5641025641025,
        "iteration": 39,
        "stdev": 69633.92249078743
    },
    "com.google.gson.functional.ObjectTest-testArrayOfObjectsSerialization": {
        "energy": 36865,
        "duration": 1092506.530612245,
        "dram": 3288.8979591836733,
        "iteration": 49,
        "stdev": 28704.63490005617
    },
    "com.google.gson.stream.JsonWriterTest-testTopLevelValueTypes": {
        "energy": 45166,
        "duration": 3330322.05,
        "dram": 10312.15,
        "iteration": 20,
        "stdev": 132179.2198585315
    },
    "com.google.gson.functional.ReadersWritersTest-testWriterForSerialization": {
        "energy": 40771,
        "duration": 2531149.4897959186,
        "dram": 7870.693877551021,
        "iteration": 49,
        "stdev": 125579.90844399828
    },
    "com.google.gson.functional.ObjectTest-testNullFieldsSerialization": {
        "energy": 38575,
        "duration": 857530.6279069767,
        "dram": 3012.1162790697676,
        "iteration": 43,
        "stdev": 7935.07682362705
    },
    "com.google.gson.functional.VersioningTest-testVersionedGsonWithUnversionedClassesSerialization": {
        "energy": 42664,
        "duration": 998381.2291666666,
        "dram": 3241.6666666666665,
        "iteration": 48,
        "stdev": 10139.127169020314
    },
    "com.google.gson.functional.EscapingTest-testGsonAcceptsEscapedAndNonEscapedJsonDeserialization": {
        "energy": 40589,
        "duration": 1162990.2307692308,
        "dram": 3589.3846153846152,
        "iteration": 52,
        "stdev": 6953.527148805245
    },
    "com.google.gson.OverrideCoreTypeAdaptersTest-testOverrideWrapperBooleanAdapter": {
        "energy": 41443,
        "duration": 4316281.62962963,
        "dram": 13373.574074074075,
        "iteration": 54,
        "stdev": 388682.83677593345
    },
    "com.google.gson.functional.PrimitiveTest-testPrimitiveBooleanAutoboxedInASingleElementArraySerialization": {
        "energy": 41076,
        "duration": 583709.8888888889,
        "dram": 2916.037037037037,
        "iteration": 27,
        "stdev": 4365.918327168543
    },
    "com.google.gson.functional.CustomTypeAdaptersTest-testCustomSerializerInvokedForPrimitives": {
        "energy": 39002,
        "duration": 882676.195652174,
        "dram": 2844.8695652173915,
        "iteration": 46,
        "stdev": 4011.05474934816
    },
    "com.google.gson.functional.JsonTreeTest-testJsonTreeNull": {
        "energy": 37842,
        "duration": 1673440.32,
        "dram": 4275.44,
        "iteration": 25,
        "stdev": 44518.849732777235
    },
    "com.google.gson.functional.PrimitiveTest-testPrimitiveBooleanAutoboxedSerialization": {
        "energy": 40954,
        "duration": 538001.5,
        "dram": 2103.8,
        "iteration": 20,
        "stdev": 3769.706307857417
    },
    "com.google.gson.functional.ObjectTest-testBagOfPrimitiveWrappersSerialization": {
        "energy": 40161,
        "duration": 1732480.5714285714,
        "dram": 4812.428571428572,
        "iteration": 49,
        "stdev": 68887.19941980059
    }
}